<?xml version="1.0" encoding="utf-8"?>
<contentitemdata.dancinggoat.newsitemcontent>
  <ContentItemDataCommonDataID>
    <GUID>918d750c-a9f1-4ee5-b25b-4e559fac201c</GUID>
    <ObjectType>cms.contentitemcommondata</ObjectType>
    <Parent>
      <CodeName>Clone_MazzerSuperJollyDR-ggk105v5</CodeName>
      <GUID>da0fb094-653e-4f29-8a4c-c2fb7f4507d4</GUID>
      <ObjectType>cms.contentitem</ObjectType>
    </Parent>
  </ContentItemDataCommonDataID>
  <ContentItemDataGUID>1ba920ea-bc4a-4f40-a3a5-a0d94d641772</ContentItemDataGUID>
  <NewsItemContentCTALabel>Buy now</NewsItemContentCTALabel>
  <NewsItemContentCTALinkURL>/products/mazzer-super-jolly-dr</NewsItemContentCTALinkURL>
  <NewsItemContentDescriptionHTML>
    <![CDATA[<p><img src="~/getContentAsset/85c64f44-4546-4327-a20a-a7934061c1b3/cc721195-df8f-4799-b974-5ade63036cab/mazer-super-jolly-dr.webp?language=en" alt="Mazzer Super Jolly DR" title="Mazzer Super Jolly DR" class="fr-fic fr-dib"></p><p>If you are a pro or at least serious about making coffee, the Mazzer Super Jolly DR is a great choice. Luxury cars are powerful and spacious; it's the same with this grinder. It provides you with a large hopper and doser with high-rev strong steel burrs powered by a 350-Watt engine.</p>]]>
  </NewsItemContentDescriptionHTML>
  <NewsItemContentPublishedDate>2024-03-10 17:40:46Z</NewsItemContentPublishedDate>
  <NewsItemContentTags>
    <![CDATA[[{"Identifier":"2fe7ed0f-2204-44c5-bcd2-3be0721b19c1"}]]]>
  </NewsItemContentTags>
  <NewsItemContentTitle>
    <![CDATA[Mazzer Super Jolly DR is a great grinder for a value price]]>
  </NewsItemContentTitle>
</contentitemdata.dancinggoat.newsitemcontent>